{
  "aarch64-darwin": {
    "buildno": "242.21829.114",
    "hash": "sha256-EUhysCfFxW2sedn/GE1rfM0KcUaCr28BV9Gtl+LXia8=",
    "live": "https://download.jetbrains.com/product?code=RR&platform=macM1&release.type=eap",
    "meta": "https://data.services.jetbrains.com/products/releases?code=RR&latest=true&type=eap",
    "variant": "-aarch64",
    "version": "2024.2"
  },
  "x86_64-darwin": {
    "buildno": "242.21829.114",
    "hash": "sha256-tILmO9hZlPiOgToQnmzAsRuXIQT6ioKVlUQFccFnMRY=",
    "live": "https://download.jetbrains.com/product?code=RR&platform=mac&release.type=eap",
    "meta": "https://data.services.jetbrains.com/products/releases?code=RR&latest=true&type=eap",
    "variant": "",
    "version": "2024.2"
  }
}
